yfunc/__init__.py
yfunc/yfunc.py
yfunc-1.0.2.dist-info/LICENSE
yfunc-1.0.2.dist-info/METADATA
yfunc-1.0.2.dist-info/WHEEL
yfunc-1.0.2.dist-info/top_level.txt
yfunc-1.0.2.dist-info/RECORD
