Metadata-Version: 2.1
Name: yfunc
Version: 1.0.2
Summary: a collection of some productive functions # b68be4fb5d6c08f5c2a34384481318996d8c76b5
Author: yzjsswk
Author-email: yzjsswk@gmail.com
Classifier: Programming Language :: Python :: 3
Classifier: License :: OSI Approved :: MIT License
Classifier: Operating System :: OS Independent
Requires-Python: >=3.11
License-File: LICENSE
Requires-Dist: clipboard
Requires-Dist: pillow
Requires-Dist: loguru
